cachefuse/__init__.py
cachefuse/cli.py
cachefuse/config.py
cachefuse/hashing.py
cachefuse/locks.py
cachefuse/serialization.py
cachefuse/api/cache.py
cachefuse/api/decorators.py
cachefuse/api/metrics.py
cachefuse/backends/base.py
cachefuse/backends/redis_backend.py
cachefuse/backends/sqlite_backend.py
cachefuse/examples/embed_demo.py
cachefuse/examples/rag_demo.py
cachefuse/tests/__init__.py
cachefuse/tests/integration/__init__.py
cachefuse/tests/integration/test_cli_commands_integration.py
cachefuse/tests/integration/test_examples_integration.py
cachefuse/tests/integration/test_redis_backend_integration.py
cachefuse/tests/integration/test_sqlite_backend_integration.py
cachefuse/tests/unit/test_cache_facade.py
cachefuse/tests/unit/test_cli.py
cachefuse/tests/unit/test_decorators.py
cachefuse/tests/unit/test_hashing.py
cachefuse/tests/unit/test_imports.py
cachefuse/tests/unit/test_locks_concurrency.py
cachefuse/tests/unit/test_metrics.py
cachefuse/tests/unit/test_privacy.py
cachefuse-0.1.0.dist-info/licenses/LICENSE
cachefuse-0.1.0.dist-info/METADATA
cachefuse-0.1.0.dist-info/WHEEL
cachefuse-0.1.0.dist-info/entry_points.txt
cachefuse-0.1.0.dist-info/top_level.txt
cachefuse-0.1.0.dist-info/RECORD
