Metadata-Version: 2.4
Name: cachefuse
Version: 0.1.0
Summary: Enterprise-grade caching framework for LLM responses and embeddings
Author-email: Yasser Elhaddar <yasser.elhaddar@example.com>
License: MIT
Keywords: cache,llm,embeddings,ai,openai,sqlite,redis,caching,performance
Classifier: Development Status :: 4 - Beta
Classifier: Intended Audience :: Developers
Classifier: Topic :: Software Development :: Libraries :: Python Modules
Classifier: Topic :: Scientific/Engineering :: Artificial Intelligence
Classifier: Programming Language :: Python :: 3
Classifier: Programming Language :: Python :: 3 :: Only
Classifier: Programming Language :: Python :: 3.9
Classifier: Programming Language :: Python :: 3.10
Classifier: Programming Language :: Python :: 3.11
Classifier: Programming Language :: Python :: 3.12
Classifier: License :: OSI Approved :: MIT License
Classifier: Operating System :: OS Independent
Requires-Python: >=3.9
License-File: LICENSE
Requires-Dist: typer>=0.12
Requires-Dist: pydantic>=2
Requires-Dist: filelock>=3.12
Requires-Dist: orjson>=3.9; platform_python_implementation != "PyPy"
Provides-Extra: redis
Requires-Dist: redis>=5; extra == "redis"
Provides-Extra: dev
Requires-Dist: pytest>=7.0; extra == "dev"
Requires-Dist: pytest-cov>=4.1; extra == "dev"
Requires-Dist: fakeredis>=2.21.0; extra == "dev"
Requires-Dist: build>=1.0.3; extra == "dev"
Requires-Dist: openai>=1.30.0; extra == "dev"
Requires-Dist: python-dotenv>=1.0.1; extra == "dev"
Requires-Dist: ipykernel>=6.29.0; extra == "dev"
Requires-Dist: sentence-transformers>=3.0.0; extra == "dev"
Dynamic: license-file
